setup.py
flask_nap.egg-info/PKG-INFO
flask_nap.egg-info/SOURCES.txt
flask_nap.egg-info/dependency_links.txt
flask_nap.egg-info/not-zip-safe
flask_nap.egg-info/pbr.json
flask_nap.egg-info/requires.txt
flask_nap.egg-info/top_level.txt
nap/__init__.py
nap/nap.py