Metadata-Version: 1.0
Name: flask-nap
Version: 0.0.1
Summary: Flask REST Framework
Home-page: https://github.com/aergener/nap
Author: Adam Ergener
Author-email: aergener@gmail.com
License: MIT
Platform: UNKNOWN
